{
  "WECHAT_MAIN_VIEWPAGER_ID": "e3l",
  "ids": {
    "ID_SELECT_PIC_LIST_VIEW": "a5h",
    "ID_COPLETE_BTN": "ch",
    "ID_SHARE_FRIEND_DIALOG_SEND_BTN": "dj6",
    "ID_SNS_CAMERA_BTN": "cj",
    "ID_HOME_ADD_BTN": "cia",
    "ID_CLICK_ADD_FRIEND": "g1l",
    "ID_CLICK_SEARCH_BOX": "bn",
    "ID_INPUT_TEXT_PHONE": "bem",
    "ID_NEW_ADD_FRIEND": "c0j",
    "ID_CONVERSATION_MORE": "cj",
    "ID_CONVERSATION_DETAIL_PP_LIST": "ayq",
    "ID_ADD_FIREND_VERIFY_SEND": "ch",
    "ID_CONVERSATION_DETAIL_CONTACT_LIST_ITEM_NAME": "evd",
    "ID_CONTACT_INFO_NAME": "azc",
    "ID_PP_DETAIL_ADD2CONTACTS": "fwd",
    "ID_ADD_FIREND_VERIFY_MESSAGE": "ewx",
    "ID_NEW_FRIEND_SEARCH_WINDOW": "ezz",
    "ID_CONTACT_SEND_INFO": "azg",
    "ID_MAIN_ADDRESSBOOK": "cij",
    "ID_ALL_LABLE": "ct3",
    "ID_SON_LABLE": "ct1",
    "ID_AUXILIARY_FUNCTION": "evl",
    "ID_MY_MAIN_IWE_PAGER": "e3l",
    "ID_START_MASS_TEXTING": "evl",
    "ID_NEW_MASS_SEND": "dfw",
    "ID_NEW_MASS_SEND_TWO": "dfu",
    "ID_RECIPIENT_TEXT_BOX": "dr3",
    "ID_CHOOSE_LABLE": "ayn",
    "ID_LABLE_FRIEND": "f2r",
    "ID_FRIEND_CHOOSE_BOX": "f2l",
    "ID_LABLE_FRIEND_ENSURE": "ch",
    "ID_MASS_NEXT_STEP": "ch",
    "ID_INPUT_TEXT_BOX": "ajs",
    "ID_INPUT_TEXT_SEND_KEYS": "amb",
    "ID_CHOOSE_ONE_GROUP": "b1f",
    "ID_GROUP_OVER_RETURN": "rj",
    "ID_ADDRESS_BOOK_LIST_VIEW": "f3",
    "ID_TRUE_DELETE_FRIEND": "dj6",
    "ID_GROUP_NAME_FROM_BUSINESS_CARD": "dmd",
    "ID_GROUP_BUSINESS_CARD_SAVE": "ch",
    "ID_CHOOSE_FRIEND_FROM_SEND_GROUP": "f2l",
    "ID_FROM_BOOK_FRIENG": "drt",
    "ID_DELETE_CHAT_MEMBER": "dgx",
    "ID_CHAT_MEMBER_CHECK": "a8y",
    "ID_CHAT_DELETE_PUSH": "ch",
    "ID_CHOOSE_GROUP_FROM_SEND_GROUP": "cc9",
    "ID_DOWN_MORE_FROM_FRIEND": "aja",
    "ID_COLLECT_CONTENT_LIST_VIEW": "btg",
    "ID_COLLECT_POPUP_WINDOWS_SEND_PUSH": "dj6",
    "ID_DOWN_MORE_LINEAR_LAYOUT": "dsb",
    "ID_CARD_SEARCH_FRIEND_BACK_PUS": "dn",
    "ID_SEARCH_TEXT_FROM_CARD": "dr3",
    "ID_SEARCH_OVER_TEXT_FROM_CARD": "g2t",
    "ID_FRIEND_CHAT_LINEAR_LAYOUT": "b5x",
    "ID_SEND_KEYS_NEWS": "ajt",
    "ID_SEARCH_FRIEND_TEXT": "bem",
    "ID_SEARCH_FRIEND_LIST_VIEW": "f13",
    "ID_SEARCH_FRIEND_LIST_VIEW_CHID_TEXT": "g2t",
    "ID_SEARCH_FRIEND_BACK_PUSH": "aac",
    "ID_HEAD_PORTRAIT_FROM_CHAT_MESSAGE": "ayq",
    "ID_MORE_FROM_FRIEND": "cj",
    "ID_DELETE_DIE_FRIEND": "b7n",
    "ID_WECHAT_ID": "azk",
    "ID_GROUP_SEE_ALL_MEMBER_GRIDVIEW": "ahm",
    "ID_NOT_ADDED_POP": "diz",
    "ID_RESEND_PUSH": "amh",
    "ID_CONTACT_NEW_FIRENDS_LISTVIEW": "c10",
    "ID_ADD_FIREND_VERIFY_REMARK": "ex0",
    "ID_SELECT_GROUP_MEMBER_NAME_TEXT": "g2t",
    "ID_DELETE_GROUP_MEMBER_NAME_TEXT": "f3c",
    "ID_MESSAGE_LIST_ITEM_AVATER": "ajc",
    "ID_CHOOSE_GROUP_ITEM_GROUP_NAME": "cc8",
    "ID_FIREND_DETAIL_LABEL_TEXT": "ax8",
    "ID_SELECT_FILE_FILE_NAME_TEXT": "cqq",
    "ID_SEE_ALL_GROUP_MEMBER_ITEM_NAME": "f23",
    "ID_NEW_FRIENDS": "c0x",
    "ID_PRESS_SPEAK": "ggb",
    "ID_SWITCH_KEYBOARD": "alt",
    "ID_SEND_COLLECT_CONTENT_SEARCH_BTN": "cj",
    "ID_SELECT_FILE_ITEM_CHECKBOX": "cqe",
    "ID_AUTOMATIC_PRAISE_LIST_VIEW": "ff7",
    "ID_AUTOMATIC_PRAISE_FRAME_LAYOUT": "fdv",
    "ID_COMMENTS_PUSH": "ij",
    "ID_COMMENTS_POPUP": "h6",
    "ID_PRAISE_PUSH": "i8",
    "ID_COMMENTS_POPUP_CLICK": "hl",
    "ID_COMMENTS_INPUT_BOX": "h7",
    "ID_COMMENTS_INPUT_TEXT_SEND_PUSH": "ha",
    "ID_PUBLIC_ACCOUNTS_NAME": "b0m",
    "ID_PUBLIC_ACCOUNTS_NO_ATTENTION": "awv",
    "ID_WECHAT_MAIN_LIST_VIEW": "dai",
    "ID_CLEA_NUNREAD_MESSAGE_READ": "g12",
    "ID_CLEA_NUNREAD_MESSAGE_READ_": "ti",
    "ID_SHARE_FRIEND_DIALOG_EDITTEXT": "avv",
    "ID_PUBLISH_EDITTEXT": "fdh",
    "ID_ALBUM_GIRD_VIEW": "dgf",
    "ID_ALBUM_GIRD_VIEW_ITEM_CHECK_BOX": "dg_",
    "ID_REMARK_TEXT": "axo",
    "ID_REMARK_EDIT": "axf",
    "ID_CONTACT_INFO_GENDER": "azh",
    "ID_CONTACT_INFO_NICK_NAME": "azb",
    "ID_SET_REMARK_LABLE_LABLE_TEXTVIEW": "ax_",
    "ID_SET_REMARK_LABLE_LABLE_VIEWGROUP": "axb",
    "ID_ADD_CONTACT_LABLE_ADD_EDITTEXT": "bem",
    "ID_NEW_FRIENDS_ACCEPT_APPLY": "c0w",
    "ID_CONVERSATION_TITLE": "dwf",
    "ID_CONVERSATION_TOP_ACCEPT_FREND_BTN": "ay3",
    "ID_CONTACT_INFO_SNS": "j_",
    "ID_USER_SNS_SPECIAL_LINE_BLACK": "cym",
    "ID_USER_SNS_ITEM_TEXT_OR_LINK": "b13",
    "ID_USER_SNS_ITEM_PIC_OR_VIDEO": "ckw",
    "ID_USER_SNS_ITEM_PIC_OR_VIDEO_DETAIL_BOTTOM_MENU": "b0y",
    "ID_ADD_FIREND_VERIFY_LABEL": "ejn",
    "ID_ADD_FIREND_VERIFY_LABEL_CONTAINER": "ejo",
    "ID_CONVERSATION_TOP_ACCEPT_FREND_AVATER": "et",
    "ID_WECHAT_WID": "b7k",
    "ID_FRIENG_CIRCLE_LINEARLAYOUT": "b0g",
    "ID_FRIEND_DYNAMIC_LINEARLAYOUT": "cxh",
    "ID_FRIEND_CIRCLE_VIDEO": "ffg",
    "ID_FRIEND_CIRCLE_SMALL_PROGRAM": "b13",
    "ID_FRIEND_CIRCLE_DAY_TEXT": "fdd",
    "ID_FRIEND_CIRCLE_MONTH_TEXT": "fec",
    "ID_FRIEND_CIRCLE_TEXT": "fde",
    "ID_FRIEND_CIRCLE_DETAILS_RECYCLERVIEW": "a5h",
    "ID_FRIEND_CIRCLE_HEART": "b0y",
    "ID_FRIEND_CIRCLE_DETAILS_PHOTO_FRAMELAYOUT": "e6i",
    "ID_FRIEND_CIRCLE_LONG_CLICK_COMPLETE": "beb",
    "ID_FRIEND_CIRCLE_SAVE_PHOTO_LIST_VIEW": "a5i",
    "ID_CIRCLE_RELEASE_LIST_VIEW": "a5h",
    "ID_CIRCLE_PHOTO_ALBUM_RELATIVELAYOUT": "evu",
    "ID_CIRCLE_PHOTO_ALBUM_CHOOSE_BOX": "dg_",
    "ID_CIRCLE_PHOTO_ALBUM_GRIDVIEW": "dgf",
    "ID_USER_SNS_TEXT": "b7d",
    "ID_USER_SNS_VIDEO_VIEW": "cj7",
    "ID_USER_SNS_VIDEO_VIEW_LITTLE": "f1c",
    "ID_USER_SNS_VIDEO_LONG_CLICK_RELATIVELAYOUT": "gd8",
    "ID_USER_SNS_VIDEO_LONG_CLICK_BOX_FRAMELAYOUT": "b7n",
    "ID_MY_WECHAT_ID": "g9v",
    "ID_WECHAT_AREA": "aza",
    "ID_WECHAT_PHONE": "e5o",
    "ID_ADD_NEW_FRIEND_MOBILE_CONTACT_ACCEPT_BTN": "c4h",
    "ID_ADD_NEW_FRIEND_MOBILE_WECHAT_NICK_NAME": "c4i",
    "ID_ADD_NEW_FRIEND_MOBILE_WECHAT_LIST_VIEW": "dk7",
    "ID_FIREND_DETAIL_DESPRATION": "awy",
    "ID_PHOTO_LONGCLICK": "epp",
    "ID_PHOTO_BACK": "f8_",
    "ID_SAVE_PHOTO_TAILOR": "bec",
    "ID_TAILOR_TRUE": "b3n",
    "ID_FILE_EXPLORER_SELECT_DIR": "buq",
    "ID_FILE_EXPLORER_SELECT_DIR_ITEM": "cqq",
    "ID_START_LOOK": "dss",
    "ID_NO_PROMPT": "cv9",
    "ID_NEAR_FRIENDS_LIST": "dsv",
    "ID_ID_NEAR_FRIENDS_NAMES": "dsw",
    "ID_MINI_MORE": "d9",
    "ID_LABELS_COUNT": "ct0",
    "ID_STEP_LIST": "blt",
    "ID_STEP_RELATIVE_LAYOUT": "b0d",
    "ID_STEP_NUMBER": "bkl",
    "ID_STEP_NAME": "bm2",
    "ID_STEP_LIKE_IMAGE": "bky",
    "ID_STEP_LIST_TEXT_INDEX": "blw",
    "ID_CHATTING_UI_TITLE": "g1r",
    "ID_MINI_GROUP_RECOMMENDED": "eca",
    "ID_MINI_PROGRAM_TEXT": "arl",
    "ID_MINI_PROGRAM": "ard",
    "ID_SNS_SINGLE_LINE_TEXT": "b7l",
    "ID_SNS_SINGLE_LINE_TEXT_DETAIL_TEXTVIEW": "fge",
    "ID_SNS_BROWSER_VIDEO_PROGRESS": "gbn",
    "ID_ADD_FRIEND_NAME": "c4f",
    "ID_SAVE_SNS_VIDEO_PROGRESS": "gcd",
    "ID_COLLECTION_SEARCH_LISTVIEW": "f12",
    "ID_FRIEND_CIRCLE_YEAR_TEXT": "fgx",
    "ID_MINI_URL_TEXT": "g2v",
    "ID_FRIEND_CIRCLE_NOTE": "b79",
    "ID_SAVE_CHAT_VIDEO_PROGRESS": "gb3",
    "ID_CHAT_LIST": "alj",
    "ID_CHAT_PHOTO": "aju",
    "ID_CHAT_VIDEO": "ami",
    "ID_CHAT_PHOTO_SAVE_VIEW": "bbm",
    "ID_CHAT_VIDEO_SAVE": "gc8",
    "ID_CHAT_LOADING_DOWN": "cjn",
    "ID_CHOOSE_ALL_FRIEND": "f2a",
    "ID_CHAT_VIDEO_MORE": "gc8",
    "ID_MY_CARD_QR_CODE": "ef7",
    "ID_MY_HEAD_PICTURE": "df4",
    "ID_MY_ADDRESS_LIST": "f6d",
    "ID_MY_ADDRESS_PHONE": "fi",
    "ID_SAVE_PHOTO_EDIT": "be4",
    "ID_CUT_LONG_VIDEO": "bdi",
    "ID_AUTOMATIC_PRAISE_LIST_VIEW_TOP": "ffe",
    "ID_MINI_CLOSE": "d8",
    "ID_GOTO_MINI": "eba",
    "ID_GROUP_CROP": "b3s",
    "ID_GROUP_ROTATING": "b49",
    "ID_GROUP_SHRINK": "b4a",
    "ID_GROUP_BIG": "b4_",
    "ID_EDITOR_IMAGE": "c5d",
    "ID_COLLECT_SEARCH_LIST": "fur",
    "ID_STEP_FRIEND_HOME_LIST": "blr",
    "ID_IMAGE_MORE_EDIT": "e6j",
    "ID_IMAGE_MORE_CHOOSE": "e6s",
    "ID_SEND_TEXT_HINT": "dp7",
    "ID_HOME_MAIN_BOTTOM": "cue",
    "ID_HOME_MAIN_BOTTOM_TEXT": "civ",
    "ID_GROUP_MODIFY_NAME": "ds_",
    "ID_NOT_FRIEND_MODIFY_LABEL": "djb",
    "ID_ADD_FRIEND_TEXT": "g1l",
    "ID_PHONE_LOADING": "d0u",
    "ID_MORE_LOADING": "d0h",
    "ID_REGISTERED_TEXT": "eo2",
    "ID_PHONE_REGISTERED_TEXT": "eo8",
    "ID_BROWSE_UI_IMAGEVIEW": "c5g"
  }
}
